skt/__init__.py
skt/gcp.py
skt/gcp_credentials.py
skt/github_utils.py
skt/hashing.py
skt/lake.py
skt/nes.py
skt/notebook_utils.py
skt/trino.py
skt/vault_utils.py
skt/ye.py
skt-1.0.10.dist-info/licenses/LICENSE
tests/__init__.py
tests/test_ye.py
skt-1.0.10.dist-info/METADATA
skt-1.0.10.dist-info/WHEEL
skt-1.0.10.dist-info/entry_points.txt
skt-1.0.10.dist-info/top_level.txt
skt-1.0.10.dist-info/RECORD
