Metadata-Version: 2.4
Name: skt
Version: 1.0.10
Summary: SKT package
Home-page: https://github.com/sktaiflow/skt
Author: SKT
Author-email: all@sktai.io
Classifier: Programming Language :: Python :: 3
Classifier: License :: OSI Approved :: MIT License
Classifier: Operating System :: OS Independent
Requires-Python: >=3.10
License-File: LICENSE
Requires-Dist: PyGithub
Requires-Dist: click
Requires-Dist: db_dtypes
Requires-Dist: google-api-python-client
Requires-Dist: google-auth-httplib2
Requires-Dist: google-auth-oauthlib
Requires-Dist: google-cloud-bigquery
Requires-Dist: google-cloud-bigquery-storage
Requires-Dist: google-cloud-iam
Requires-Dist: google-cloud-storage
Requires-Dist: hmsclient
Requires-Dist: httplib2
Requires-Dist: hvac
Requires-Dist: numpy
Requires-Dist: packaging
Requires-Dist: pandas
Requires-Dist: pandas-gbq
Requires-Dist: pyarrow
Requires-Dist: pydata-google-auth
Requires-Dist: tabulate
Requires-Dist: tqdm
Requires-Dist: trino[sqlalchemy]
Requires-Dist: jupysql
Provides-Extra: dev
Requires-Dist: pytest; extra == "dev"
Provides-Extra: spark
Requires-Dist: pyspark[sql]<4.0.0; extra == "spark"
Dynamic: author
Dynamic: author-email
Dynamic: classifier
Dynamic: description
Dynamic: description-content-type
Dynamic: home-page
Dynamic: license-file
Dynamic: provides-extra
Dynamic: requires-dist
Dynamic: requires-python
Dynamic: summary
